api_base/__init__.py
api_base-1.0.1.dist-info/METADATA
api_base-1.0.1.dist-info/WHEEL
api_base-1.0.1.dist-info/entry_points.txt
api_base-1.0.1.dist-info/top_level.txt
api_base-1.0.1.dist-info/RECORD
